ai_api_client_sdk/__init__.py
ai_api_client_sdk/ai_api_v2_client.py
ai_api_client_sdk/exception.py
ai_api_client_sdk/helpers/__init__.py
ai_api_client_sdk/helpers/authenticator.py
ai_api_client_sdk/helpers/constants.py
ai_api_client_sdk/helpers/datetime_parser.py
ai_api_client_sdk/helpers/llm_helper.py
ai_api_client_sdk/helpers/logging.py
ai_api_client_sdk/helpers/rest_client.py
ai_api_client_sdk/models/__init__.py
ai_api_client_sdk/models/ai_api_capabilities.py
ai_api_client_sdk/models/ai_api_capabilities_bulk_updates.py
ai_api_client_sdk/models/ai_api_capabilities_logs.py
ai_api_client_sdk/models/ai_api_limits.py
ai_api_client_sdk/models/ai_api_limits_deployments.py
ai_api_client_sdk/models/ai_api_limits_enactments.py
ai_api_client_sdk/models/ai_api_limits_executions.py
ai_api_client_sdk/models/ai_api_meta.py
ai_api_client_sdk/models/api_version.py
ai_api_client_sdk/models/artifact.py
ai_api_client_sdk/models/artifact_create_response.py
ai_api_client_sdk/models/artifact_query_response.py
ai_api_client_sdk/models/base_models.py
ai_api_client_sdk/models/capabilities.py
ai_api_client_sdk/models/configuration.py
ai_api_client_sdk/models/configuration_create_response.py
ai_api_client_sdk/models/configuration_query_response.py
ai_api_client_sdk/models/dataset_capabilities.py
ai_api_client_sdk/models/dataset_limits.py
ai_api_client_sdk/models/deployment.py
ai_api_client_sdk/models/deployment_bulk_modify_response.py
ai_api_client_sdk/models/deployment_create_response.py
ai_api_client_sdk/models/deployment_get_status_response.py
ai_api_client_sdk/models/deployment_query_response.py
ai_api_client_sdk/models/enactment.py
ai_api_client_sdk/models/enactment_get_status_response.py
ai_api_client_sdk/models/executable.py
ai_api_client_sdk/models/executable_query_response.py
ai_api_client_sdk/models/execution.py
ai_api_client_sdk/models/execution_bulk_modify_response.py
ai_api_client_sdk/models/execution_create_response.py
ai_api_client_sdk/models/execution_get_status_response.py
sap_ai_sdk_base-3.1.3.dist-info/LICENSE
sap_ai_sdk_base-3.1.3.dist-info/METADATA
sap_ai_sdk_base-3.1.3.dist-info/WHEEL
sap_ai_sdk_base-3.1.3.dist-info/top_level.txt
sap_ai_sdk_base-3.1.3.dist-info/RECORD
